{"type": "Group",
 "name": "Z_2 x Z_2 x Z_2",
 "description": "no description",
 "element_names": ["eee", "aee", "eae", "aae", "eea", "aea", "eaa", "aaa"],
 "addition_table": [[0, 1, 2, 3, 4, 5, 6, 7],
                    [1, 0, 3, 2, 5, 4, 7, 6],
                    [2, 3, 0, 1, 6, 7, 4, 5],
                    [3, 2, 1, 0, 7, 6, 5, 4],
                    [4, 5, 6, 7, 0, 1, 2, 3],
                    [5, 4, 7, 6, 1, 0, 3, 2],
                    [6, 7, 4, 5, 2, 3, 0, 1],
                    [7, 6, 5, 4, 3, 2, 1, 0]]
}
